hccinfhir/__init__.py
hccinfhir/constants.py
hccinfhir/datamodels.py
hccinfhir/defaults.py
hccinfhir/extractor.py
hccinfhir/extractor_834.py
hccinfhir/extractor_837.py
hccinfhir/extractor_fhir.py
hccinfhir/filter.py
hccinfhir/hccinfhir.py
hccinfhir/model_calculate.py
hccinfhir/model_coefficients.py
hccinfhir/model_demographics.py
hccinfhir/model_dx_to_cc.py
hccinfhir/model_hierarchies.py
hccinfhir/model_interactions.py
hccinfhir/samples.py
hccinfhir/utils.py
hccinfhir/data/__init__.py
hccinfhir/data/hcc_is_chronic.csv
hccinfhir/data/hcc_is_chronic_without_esrd_model.csv
hccinfhir/data/ph_race_and_ethnicity_cdc_v1.3.csv
hccinfhir/data/ra_coefficients_2025.csv
hccinfhir/data/ra_coefficients_2026.csv
hccinfhir/data/ra_dx_to_cc_2025.csv
hccinfhir/data/ra_dx_to_cc_2026.csv
hccinfhir/data/ra_eligible_cpt_hcpcs_2023.csv
hccinfhir/data/ra_eligible_cpt_hcpcs_2024.csv
hccinfhir/data/ra_eligible_cpt_hcpcs_2025.csv
hccinfhir/data/ra_eligible_cpt_hcpcs_2026.csv
hccinfhir/data/ra_hierarchies_2025.csv
hccinfhir/data/ra_hierarchies_2026.csv
hccinfhir/data/ra_labels_2026.csv
hccinfhir/sample_files/__init__.py
hccinfhir/sample_files/sample_834_01.txt
hccinfhir/sample_files/sample_834_02.txt
hccinfhir/sample_files/sample_834_03.txt
hccinfhir/sample_files/sample_834_04.txt
hccinfhir/sample_files/sample_834_05.txt
hccinfhir/sample_files/sample_834_06.txt
hccinfhir/sample_files/sample_837_0.txt
hccinfhir/sample_files/sample_837_1.txt
hccinfhir/sample_files/sample_837_10.txt
hccinfhir/sample_files/sample_837_11.txt
hccinfhir/sample_files/sample_837_12.txt
hccinfhir/sample_files/sample_837_2.txt
hccinfhir/sample_files/sample_837_3.txt
hccinfhir/sample_files/sample_837_4.txt
hccinfhir/sample_files/sample_837_5.txt
hccinfhir/sample_files/sample_837_6.txt
hccinfhir/sample_files/sample_837_7.txt
hccinfhir/sample_files/sample_837_8.txt
hccinfhir/sample_files/sample_837_9.txt
hccinfhir/sample_files/sample_eob_1.json
hccinfhir/sample_files/sample_eob_2.json
hccinfhir-0.2.8.dist-info/METADATA
hccinfhir-0.2.8.dist-info/WHEEL
hccinfhir-0.2.8.dist-info/licenses/LICENSE
hccinfhir-0.2.8.dist-info/RECORD
