Metadata-Version: 2.3
Name: hccinfhir
Version: 0.2.8
Summary: HCC Algorithm for FHIR Resources
Project-URL: Homepage, https://github.com/mimilabs/hccinfhir
Project-URL: Issues, https://github.com/mimilabs/hccinfhir/issues
Author-email: Yubin Park <yubin.park@mimilabs.ai>
Classifier: License :: OSI Approved :: Apache Software License
Classifier: Operating System :: OS Independent
Classifier: Programming Language :: Python :: 3
Requires-Python: >=3.8
Requires-Dist: pydantic>=2.10.3
Requires-Dist: typing-extensions>=4.6.0
